setup.py
getLatLng/__init__.py
getLatLng/latlng.py
getLatLng.egg-info/PKG-INFO
getLatLng.egg-info/SOURCES.txt
getLatLng.egg-info/dependency_links.txt
getLatLng.egg-info/not-zip-safe
getLatLng.egg-info/requires.txt
getLatLng.egg-info/top_level.txt