Metadata-Version: 1.0
Name: getLatLng
Version: 1.0.0
Summary: Directory to get latitude and longitude values of particular city.
Home-page: https://github.com/36rahu/pincode_directory
Author: Piyush Wanare
Author-email: piyushwanare24@gmail.com
License: MIT
Platform: UNKNOWN
